a0g/__init__.py
a0g/base.py
a0g/common/__init__.py
a0g/common/utils.py
a0g/contract/__init__.py
a0g/d402/__init__.py
a0g/d402/ratings/__init__.py
a0g/d402/ratings/base.py
a0g/d402/ratings/onchain.py
a0g/d402/ratings/simple.py
a0g/d402/tool_verifier.py
a0g/health/__init__.py
a0g/jsbindings/CLAUDE.md
a0g/jsbindings/dist/bundle.js
a0g/jsbindings/package.json
a0g/jsbindings/pnpm-lock.yaml
a0g/jsbindings/src/index.ts
a0g/jsbindings/src/typechain/factories/FineTuningServing__factory.js
a0g/jsbindings/src/typechain/factories/InferenceServing__factory.js
a0g/jsbindings/src/typechain/factories/LedgerManager__factory.js
a0g/jsbindings/src/typechain/factories/index.ts
a0g/jsbindings/src/types/contracts.ts
a0g/jsbindings/tsconfig.json
a0g/types/__init__.py
a0g/types/account.py
a0g/types/headers.py
a0g/types/ledger.py
a0g/types/model.py
a0g/types/settle_signer_key.py
a0g/types/storage.py
python_0g-0.6.1.2.dist-info/METADATA
python_0g-0.6.1.2.dist-info/WHEEL
python_0g-0.6.1.2.dist-info/licenses/LICENSE
python_0g-0.6.1.2.dist-info/RECORD
