Metadata-Version: 2.4
Name: python-0g
Version: 0.6.1.2
Summary: Official Python 0g.ai package for Inference & Storage SDK
License-File: LICENSE
Author: George Kasparyants
Author-email: gg_plastt@mail.ru
Requires-Python: >=3.10,<4.0
Classifier: Programming Language :: Python :: 3
Classifier: Programming Language :: Python :: 3.10
Classifier: Programming Language :: Python :: 3.11
Classifier: Programming Language :: Python :: 3.12
Classifier: Programming Language :: Python :: 3.13
Classifier: Programming Language :: Python :: 3.14
Provides-Extra: langchain
Requires-Dist: javascript (>=1!1.2.6,<1!2.0.0)
Requires-Dist: langchain (>=1.2.0,<2.0.0) ; extra == "langchain"
Requires-Dist: langchain-core (>=1.2.2,<2.0.0) ; extra == "langchain"
Requires-Dist: langchain-openai (>=1.1.5,<2.0.0) ; extra == "langchain"
Requires-Dist: notebook (>=7.5.0,<8.0.0)
Requires-Dist: openai (>=1.109.1,<2.0.0)
Requires-Dist: web3 (>=7.13.0,<8.0.0)
